Metadata-Version: 1.1
Name: sampleaoao
Version: 1.0.1
Summary: A sample Python projectaaa
Home-page: https://github.com/melissashopes/sampleproject
Author: authhhh
Author-email: UNKNOWN
License: MIT
Keywords: sample setuptools development
Platform: UNKNOWN
Classifier: Development Status :: 3 - Alpha
Classifier: Intended Audience :: Developers
Classifier: Topic :: Software Development :: Build Tools
Classifier: License :: OSI Approved :: MIT License
Classifier: Programming Language :: Python :: 2
Classifier: Programming Language :: Python :: 2.7
Classifier: Programming Language :: Python :: 3
Classifier: Programming Language :: Python :: 3.3
Classifier: Programming Language :: Python :: 3.4
Classifier: Programming Language :: Python :: 3.5
